MANIFEST.in
README.md
lgpl-2.1.txt
setup.cfg
setup.py
MeshLabXML.egg-info/PKG-INFO
MeshLabXML.egg-info/SOURCES.txt
MeshLabXML.egg-info/dependency_links.txt
MeshLabXML.egg-info/top_level.txt
examples/CC0.txt
examples/quatrefoil_voronoi.py
examples/shield.py
meshlabxml/__init__.py
meshlabxml/clean.py
meshlabxml/color_names.py
meshlabxml/color_names.txt
meshlabxml/compute.py
meshlabxml/create.py
meshlabxml/delete.py
meshlabxml/files.py
meshlabxml/layers.py
meshlabxml/mlx.py
meshlabxml/mp_func.py
meshlabxml/normals.py
meshlabxml/remesh.py
meshlabxml/sampling.py
meshlabxml/select.py
meshlabxml/smooth.py
meshlabxml/subdivide.py
meshlabxml/texture.py
meshlabxml/transfer.py
meshlabxml/transform.py
meshlabxml/util.py
meshlabxml/vert_color.py
models/bunny.txt
models/bunny_flat(1Z).ply
models/bunny_raw(-1250Y).ply