Metadata-Version: 1.0
Name: MeshLabXML
Version: 2017.9
Summary: Create and run MeshLab XML scripts
Home-page: https://github.com/3DLIRIOUS/MeshLabXML
Author: 3DLirious
Author-email: 3DLirious@gmail.com
License: LGPL-2.1
Platform: UNKNOWN
